{
    "uuid": "89a78501-50bb-4bad-944f-31040ddde22e",
    "shortName": "battery-monitor",
    "longName": "battery-monitor",
    "companyName": "Ave Wrigley",
    "versionCode": 31,
    "versionLabel": "1.0.31",
    "watchapp": {
        "watchface": true
    },
    "appKeys": {
        "temp": 2,
        "city": 3,
        "description": 4,
        "tap_to_update": 5,
        "clock_format": 6,
        "icon": 7,
        "fetch_weather": 8,
        "datestamp": 9
    },    
    "capabilities": [ "location", "configurable" ],
    "resources": {
        "media": [
        [% FOREACH image IN images %]
            {
                "type": "png",
                "name": "[% image.name %]",
                "file": "[% image.file %]"
            },
        [% END %]
            {
                "type": "png",
                "name": "BATTERY_25",
                "file": "img/battery_25_percent.png"
            },
            {
                "type": "png",
                "name": "BATTERY_50",
                "file": "img/battery_50_percent.png"
            },
            {
                "type": "png",
                "name": "BATTERY_75",
                "file": "img/battery_75_percent.png"
            },
            {
                "type": "png",
                "name": "BATTERY_100",
                "file": "img/battery_100_percent.png"
            },
            {
                "type": "png",
                "name": "BATTERY_CHARGING",
                "file": "img/battery_charging.png"
            },
            {
                "type": "font",
                "name": "FONT_CONSOLA_MONO_36",
                "file": "fonts/consolamono/ConsolaMono_36.ttf"
            }, 
            {
                "type": "font",
                "name": "FONT_CONSOLA_MONO_20",
                "file": "fonts/consolamono/ConsolaMono_20.ttf"
            }, 
            {
                "type": "font",
                "name": "FONT_ANON_PRO_B_36",
                "file": "fonts/anon-pro/anon-pro-B_36.ttf"
            }, 
            {
                "type": "font",
                "name": "FONT_ANON_PRO_B_20",
                "file": "fonts/anon-pro/anon-pro-B_20.ttf"
            } 

        ]
    }
}
